README.md
setup.py
br_address_parser/__init__.py
br_address_parser/parser.py
br_address_parser.egg-info/PKG-INFO
br_address_parser.egg-info/SOURCES.txt
br_address_parser.egg-info/dependency_links.txt
br_address_parser.egg-info/requires.txt
br_address_parser.egg-info/top_level.txt