Metadata-Version: 2.1
Name: br-address-parser
Version: 0.1.0
Summary: UNKNOWN
Home-page: https://github.com/brain-facens/br-address-parser
Author: Emanuel Huber
Author-email: emanuel.tesv@gmail.com
License: MIT
Keywords: br-address,address,address-parser
Platform: UNKNOWN
Provides-Extra: dev
